{
  "version": 2,
  "actions": [
    "create", "review", "debug", "refactor", "explain",
    "test", "document", "optimize", "design", "fix"
  ],
  "objects": [
    "code", "function", "file", "component", "test", "PR",
    "commit", "API", "schema", "prompt", "config", "error",
    "architecture", "database"
  ],
  "categories": [
    "coding", "ai-workflows", "research", "automation",
    "content", "productivity"
  ],
  "action_synonyms": {
    "create": ["build", "make", "generate", "write", "implement", "add", "scaffold"],
    "review": ["check", "audit", "look at", "examine", "inspect", "evaluate"],
    "debug": ["fix", "troubleshoot", "investigate", "diagnose", "trace", "find bug"],
    "refactor": ["clean up", "restructure", "reorganize", "improve", "simplify"],
    "explain": ["what is", "how does", "why", "describe", "tell me about", "walk through"],
    "test": ["write tests", "add tests", "test coverage", "unit test", "integration test"],
    "document": ["add docs", "document", "write docs", "JSDoc", "README"],
    "optimize": ["speed up", "improve performance", "make faster", "reduce", "profile"],
    "design": ["architect", "plan", "structure", "model", "blueprint"],
    "fix": ["resolve", "repair", "patch", "correct", "handle"]
  },
  "object_synonyms": {
    "code": ["codebase", "source", "implementation", "logic"],
    "function": ["method", "handler", "callback", "routine", "procedure"],
    "file": ["module", "script", "source file"],
    "component": ["widget", "element", "view", "page", "screen"],
    "test": ["spec", "test suite", "test case", "unit test"],
    "API": ["endpoint", "route", "REST", "GraphQL", "service"],
    "error": ["bug", "issue", "exception", "crash", "failure"],
    "config": ["configuration", "settings", "env", "environment"]
  },
  "domain_synonyms": {
    "web": {
      "action_synonyms": {
        "create": ["scaffold", "bootstrap", "init"],
        "optimize": ["lighthouse", "lazy load", "code split"]
      },
      "object_synonyms": {
        "component": ["page", "layout", "route"],
        "API": ["endpoint", "handler", "middleware"]
      }
    },
    "data": {
      "action_synonyms": {
        "optimize": ["vectorize", "batch", "cache", "index"],
        "create": ["pipeline", "etl", "ingest"]
      },
      "object_synonyms": {
        "database": ["table", "collection", "index", "query"],
        "schema": ["model", "migration", "seed"]
      }
    },
    "devops": {
      "action_synonyms": {
        "create": ["provision", "deploy", "spin up"],
        "debug": ["triage", "incident", "on-call"]
      },
      "object_synonyms": {
        "config": ["dockerfile", "compose", "helm", "terraform"]
      }
    }
  },
  "domain_map": {
    "typescript": "web",
    "javascript": "web",
    "python": "data",
    "go": "devops",
    "rust": "devops",
    "java": "web"
  },
  "framework_domain_override": {
    "nextjs": "web",
    "react": "web",
    "vue": "web",
    "svelte": "web",
    "express": "web",
    "fastapi": "web",
    "django": "web",
    "flask": "web"
  }
}
